{
    "version": "1.7.3",
    "description": "Railway's CLI",
    "homepage": "https://github.com/railwayapp/cli",
    "license": "MIT",
    "architecture": {
        "64bit": {
            "url": "https://github.com/railwayapp/cli/releases/download/v1.7.3/railway_1.7.3_windows_amd64.tar.gz",
            "hash": "1f734e9da67e70df97c5cfb1277a8defa689876b4919d0374385803e3b0fdb3a"
        }
    },
    "bin": "railway.exe",
    "checkver": "github",
    "autoupdate": {
        "architecture": {
            "64bit": {
                "url": "https://github.com/railwayapp/cli/releases/download/v$version/railway_$version_windows_amd64.tar.gz"
            }
        },
        "hash": {
            "url": "$url.sha256"
        }
    }
}
